mixes/DGMM.py
mixes/Evaluator.py
mixes/GMM.py
mixes/GMN.py
mixes/SkewGMM.py
mixes/__init__.py
mixes/stopping_criterion.py
mixes/tests.py
mixes/utils.py
mixes-1.0.dist-info/METADATA
mixes-1.0.dist-info/WHEEL
mixes-1.0.dist-info/top_level.txt
mixes-1.0.dist-info/RECORD
