Metadata-Version: 2.1
Name: mixes
Version: 1.0
Summary: A package of mixture models including Skew GMM, GMN and DGMM
Author-email: Andriy Dmytruk <Andr.Dmytruk@gmail.com>
Project-URL: Homepage, https://github.com/KangaroosInAntarcitica/mixes
Keywords: mixture models,GMN,DGMM,Skew GMM,GMM
Classifier: License :: OSI Approved :: MIT License
Classifier: Programming Language :: Python
Classifier: Programming Language :: Python :: 3
Requires-Python: >=3.0
Requires-Dist: scikit-learn (>=0.24.1)
Requires-Dist: numpy (>=1.20.1)
Requires-Dist: scipy (>=1.6.2)
Provides-Extra: dataframes
Requires-Dist: pandas (>=1.2.4) ; extra == 'dataframes'
Provides-Extra: plotting
Requires-Dist: matplotlib (>=3.3.4) ; extra == 'plotting'
